lowresnltk/__init__.py
lowresnltk/main.py
lowresnltk/pos_tagger.py
lowresnltk/sentence_classifier.py
lowresnltk-1.1.1.dist-info/licenses/LICENSE.txt
lowresnltk-1.1.1.dist-info/METADATA
lowresnltk-1.1.1.dist-info/WHEEL
lowresnltk-1.1.1.dist-info/top_level.txt
lowresnltk-1.1.1.dist-info/RECORD
