Metadata-Version: 2.4
Name: lowresnltk
Version: 1.1.1
Summary: Low Resource NLTK
Author-email: abkafi1234 <kafi.cse@diu.edu.bd>
License: MIT
Project-URL: Homepage, https://github.com/abkafi1234/lowresnltk
Project-URL: Repository, https://github.com/abkafi1234/lowresnltk
Project-URL: Issues, https://github.com/abkafi1234/lowresnltk/issues
Classifier: Programming Language :: Python :: 3
Classifier: License :: OSI Approved :: MIT License
Classifier: Operating System :: OS Independent
Classifier: Intended Audience :: Developers
Requires-Python: >=3.8
License-File: LICENSE.txt
Requires-Dist: torch
Requires-Dist: transformers
Requires-Dist: numpy
Requires-Dist: pandas
Requires-Dist: scikit-learn
Requires-Dist: accelerate
Dynamic: license-file
